[
    {
        "time": 42.072,
        "pitch": 57
    },
    {
        "time": 42.392,
        "pitch": 62
    },
    {
        "time": 42.541,
        "pitch": 64
    },
    {
        "time": 42.841,
        "pitch": 63
    },
    {
        "time": 43.544,
        "pitch": 61
    },
    {
        "time": 43.698,
        "pitch": 63
    },
    {
        "time": 43.773,
        "pitch": 61
    },
    {
        "time": 44.01,
        "pitch": 58
    },
    {
        "time": 45.128,
        "pitch": 72
    },
    {
        "time": 45.2,
        "pitch": 71
    },
    {
        "time": 45.274,
        "pitch": 70
    },
    {
        "time": 45.422,
        "pitch": 69
    },
    {
        "time": 45.572,
        "pitch": 68
    },
    {
        "time": 45.735,
        "pitch": 60
    },
    {
        "time": 45.896,
        "pitch": 61
    },
    {
        "time": 46.044,
        "pitch": 62
    },
    {
        "time": 46.193,
        "pitch": 67
    },
    {
        "time": 46.353,
        "pitch": 66
    },
    {
        "time": 46.503,
        "pitch": 65
    },
    {
        "time": 46.641,
        "pitch": 63
    },
    {
        "time": 46.909,
        "pitch": 65
    },
    {
        "time": 46.972,
        "pitch": 63
    },
    {
        "time": 47.037,
        "pitch": 58
    },
    {
        "time": 47.165,
        "pitch": 56
    },
    {
        "time": 47.295,
        "pitch": 55
    },
    {
        "time": 47.609,
        "pitch": 70
    },
    {
        "time": 47.757,
        "pitch": 71
    },
    {
        "time": 47.83,
        "pitch": 70
    },
    {
        "time": 47.907,
        "pitch": 66
    },
    {
        "time": 48.064,
        "pitch": 65
    },
    {
        "time": 48.218,
        "pitch": 63
    },
    {
        "time": 48.372,
        "pitch": 61
    },
    {
        "time": 48.527,
        "pitch": 62
    },
    {
        "time": 49.099,
        "pitch": 58
    },
    {
        "time": 50.543,
        "pitch": 65
    },
    {
        "time": 50.64,
        "pitch": 67
    },
    {
        "time": 50.734,
        "pitch": 70
    },
    {
        "time": 50.833,
        "pitch": 74
    },
    {
        "time": 51.286,
        "pitch": 77
    },
    {
        "time": 51.428,
        "pitch": 74
    },
    {
        "time": 51.575,
        "pitch": 67
    },
    {
        "time": 51.87,
        "pitch": 73
    },
    {
        "time": 52.175,
        "pitch": 67
    },
    {
        "time": 53.272,
        "pitch": 61
    },
    {
        "time": 53.409,
        "pitch": 62
    },
    {
        "time": 53.489,
        "pitch": 65
    },
    {
        "time": 53.566,
        "pitch": 67
    },
    {
        "time": 53.643,
        "pitch": 69
    },
    {
        "time": 53.724,
        "pitch": 72
    },
    {
        "time": 53.801,
        "pitch": 70
    },
    {
        "time": 53.874,
        "pitch": 69
    },
    {
        "time": 53.947,
        "pitch": 67
    },
    {
        "time": 54.022,
        "pitch": 66
    },
    {
        "time": 54.083,
        "pitch": 67
    },
    {
        "time": 54.142,
        "pitch": 70
    },
    {
        "time": 54.201,
        "pitch": 67
    },
    {
        "time": 54.263,
        "pitch": 63
    },
    {
        "time": 54.34,
        "pitch": 62
    },
    {
        "time": 54.406,
        "pitch": 60
    },
    {
        "time": 54.472,
        "pitch": 58
    },
    {
        "time": 54.541,
        "pitch": 57
    },
    {
        "time": 54.618,
        "pitch": 60
    },
    {
        "time": 54.691,
        "pitch": 62
    },
    {
        "time": 54.765,
        "pitch": 66
    },
    {
        "time": 54.842,
        "pitch": 65
    },
    {
        "time": 55.285,
        "pitch": 63
    },
    {
        "time": 55.44,
        "pitch": 62
    },
    {
        "time": 55.591,
        "pitch": 58
    },
    {
        "time": 55.734,
        "pitch": 59
    },
    {
        "time": 55.895,
        "pitch": 60
    },
    {
        "time": 56.057,
        "pitch": 56
    },
    {
        "time": 56.183,
        "pitch": 54
    },
    {
        "time": 56.309,
        "pitch": 55
    },
    {
        "time": 56.407,
        "pitch": 58
    },
    {
        "time": 56.503,
        "pitch": 60
    },
    {
        "time": 56.603,
        "pitch": 61
    },
    {
        "time": 56.764,
        "pitch": 58
    },
    {
        "time": 56.915,
        "pitch": 60
    },
    {
        "time": 57.074,
        "pitch": 61
    },
    {
        "time": 57.234,
        "pitch": 60
    },
    {
        "time": 57.288,
        "pitch": 61
    },
    {
        "time": 57.338,
        "pitch": 60
    },
    {
        "time": 57.387,
        "pitch": 58
    },
    {
        "time": 57.538,
        "pitch": 61
    },
    {
        "time": 57.662,
        "pitch": 58
    },
    {
        "time": 57.787,
        "pitch": 60
    },
    {
        "time": 57.949,
        "pitch": 58
    },
    {
        "time": 58.1,
        "pitch": 57
    },
    {
        "time": 58.198,
        "pitch": 58
    },
    {
        "time": 58.292,
        "pitch": 60
    },
    {
        "time": 58.39,
        "pitch": 62
    },
    {
        "time": 58.53,
        "pitch": 58
    },
    {
        "time": 60.214,
        "pitch": 72
    },
    {
        "time": 60.28,
        "pitch": 70
    },
    {
        "time": 60.349,
        "pitch": 69
    },
    {
        "time": 60.492,
        "pitch": 74
    },
    {
        "time": 60.637,
        "pitch": 75
    },
    {
        "time": 60.785,
        "pitch": 70
    },
    {
        "time": 60.932,
        "pitch": 67
    },
    {
        "time": 61.088,
        "pitch": 63
    },
    {
        "time": 61.246,
        "pitch": 62
    },
    {
        "time": 61.387,
        "pitch": 66
    },
    {
        "time": 61.52,
        "pitch": 69
    },
    {
        "time": 61.662,
        "pitch": 72
    },
    {
        "time": 61.806,
        "pitch": 70
    },
    {
        "time": 61.946,
        "pitch": 66
    },
    {
        "time": 62.085,
        "pitch": 63
    },
    {
        "time": 62.224,
        "pitch": 60
    },
    {
        "time": 62.365,
        "pitch": 59
    },
    {
        "time": 62.505,
        "pitch": 62
    },
    {
        "time": 62.57,
        "pitch": 65
    },
    {
        "time": 62.637,
        "pitch": 69
    },
    {
        "time": 62.772,
        "pitch": 65
    },
    {
        "time": 62.908,
        "pitch": 70
    },
    {
        "time": 63.047,
        "pitch": 66
    },
    {
        "time": 63.185,
        "pitch": 63
    },
    {
        "time": 63.324,
        "pitch": 60
    },
    {
        "time": 63.465,
        "pitch": 59
    },
    {
        "time": 63.56,
        "pitch": 62
    },
    {
        "time": 63.643,
        "pitch": 65
    },
    {
        "time": 63.73,
        "pitch": 69
    },
    {
        "time": 64.025,
        "pitch": 75
    },
    {
        "time": 64.102,
        "pitch": 73
    },
    {
        "time": 64.174,
        "pitch": 71
    },
    {
        "time": 64.246,
        "pitch": 68
    },
    {
        "time": 64.322,
        "pitch": 65
    },
    {
        "time": 65.069,
        "pitch": 64
    },
    {
        "time": 65.139,
        "pitch": 65
    },
    {
        "time": 65.213,
        "pitch": 67
    },
    {
        "time": 65.288,
        "pitch": 69
    },
    {
        "time": 65.359,
        "pitch": 70
    },
    {
        "time": 65.43,
        "pitch": 72
    },
    {
        "time": 65.504,
        "pitch": 74
    },
    {
        "time": 65.645,
        "pitch": 72
    },
    {
        "time": 65.787,
        "pitch": 70
    },
    {
        "time": 65.948,
        "pitch": 69
    },
    {
        "time": 66.098,
        "pitch": 67
    },
    {
        "time": 66.23,
        "pitch": 65
    },
    {
        "time": 66.363,
        "pitch": 64
    },
    {
        "time": 66.461,
        "pitch": 67
    },
    {
        "time": 66.553,
        "pitch": 69
    },
    {
        "time": 66.649,
        "pitch": 74
    },
    {
        "time": 66.8,
        "pitch": 73
    },
    {
        "time": 66.954,
        "pitch": 72
    },
    {
        "time": 67.101,
        "pitch": 71
    },
    {
        "time": 67.24,
        "pitch": 70
    },
    {
        "time": 67.391,
        "pitch": 69
    },
    {
        "time": 67.543,
        "pitch": 67
    },
    {
        "time": 67.681,
        "pitch": 65
    },
    {
        "time": 67.818,
        "pitch": 63
    },
    {
        "time": 67.968,
        "pitch": 55
    },
    {
        "time": 68.121,
        "pitch": 58
    },
    {
        "time": 68.274,
        "pitch": 62
    },
    {
        "time": 68.418,
        "pitch": 60
    },
    {
        "time": 68.569,
        "pitch": 58
    },
    {
        "time": 68.72,
        "pitch": 57
    },
    {
        "time": 68.812,
        "pitch": 60
    },
    {
        "time": 68.9,
        "pitch": 63
    },
    {
        "time": 68.99,
        "pitch": 65
    },
    {
        "time": 69.059,
        "pitch": 66
    },
    {
        "time": 69.125,
        "pitch": 65
    },
    {
        "time": 70.399,
        "pitch": 64
    },
    {
        "time": 70.565,
        "pitch": 63
    },
    {
        "time": 71.832,
        "pitch": 60
    },
    {
        "time": 72.134,
        "pitch": 58
    },
    {
        "time": 72.291,
        "pitch": 56
    },
    {
        "time": 72.447,
        "pitch": 55
    },
    {
        "time": 72.583,
        "pitch": 54
    },
    {
        "time": 72.72,
        "pitch": 53
    },
    {
        "time": 72.872,
        "pitch": 52
    },
    {
        "time": 73.014,
        "pitch": 51
    },
    {
        "time": 73.158,
        "pitch": 53
    },
    {
        "time": 73.304,
        "pitch": 62
    },
    {
        "time": 73.846,
        "pitch": 60
    },
    {
        "time": 74.002,
        "pitch": 59
    },
    {
        "time": 74.148,
        "pitch": 58
    },
    {
        "time": 74.293,
        "pitch": 57
    },
    {
        "time": 74.44,
        "pitch": 56
    },
    {
        "time": 74.59,
        "pitch": 55
    },
    {
        "time": 74.738,
        "pitch": 54
    },
    {
        "time": 74.885,
        "pitch": 58
    },
    {
        "time": 75.033,
        "pitch": 65
    },
    {
        "time": 75.176,
        "pitch": 63
    },
    {
        "time": 76.713,
        "pitch": 65
    },
    {
        "time": 76.807,
        "pitch": 67
    },
    {
        "time": 76.897,
        "pitch": 70
    },
    {
        "time": 76.989,
        "pitch": 73
    },
    {
        "time": 77.133,
        "pitch": 75
    },
    {
        "time": 77.203,
        "pitch": 73
    },
    {
        "time": 77.278,
        "pitch": 70
    },
    {
        "time": 77.435,
        "pitch": 72
    },
    {
        "time": 77.581,
        "pitch": 70
    },
    {
        "time": 77.727,
        "pitch": 69
    },
    {
        "time": 77.875,
        "pitch": 67
    },
    {
        "time": 78.031,
        "pitch": 65
    },
    {
        "time": 78.185,
        "pitch": 63
    },
    {
        "time": 78.332,
        "pitch": 58
    },
    {
        "time": 78.48,
        "pitch": 62
    }
]